CHANGELOG.txt
LICENCE.txt
MANIFEST.in
README.txt
all_movies.pkl
example.ipynb
setup.py
.ipynb_checkpoints/example-checkpoint.ipynb
movieFinder/__init__.py
movieFinder/download_movies.py
movieFinder/moviefinder.py
movieFinder.egg-info/SOURCES.txt
movieFinder.egg-info/dependency_links.txt
movieFinder.egg-info/requires.txt
movieFinder.egg-info/top_level.txt
movieFinderIMDB.egg-info/PKG-INFO
movieFinderIMDB.egg-info/SOURCES.txt
movieFinderIMDB.egg-info/dependency_links.txt
movieFinderIMDB.egg-info/requires.txt
movieFinderIMDB.egg-info/top_level.txt
movieFinder/.ipynb_checkpoints/__init__-checkpoint.py
movieFinder/.ipynb_checkpoints/download_movies-checkpoint.py
movieFinder/.ipynb_checkpoints/moviefinder-checkpoint.py